commonz/animasnd/audio.py
commonz/animasnd/image.py
commonz/animasnd/video.py
commonz/codec/codec.py
commonz/codec/condensat.py
commonz/codec/crypto.py
commonz/config/__init__.py
commonz/config/config.py
commonz/constants/__init__.py
commonz/constants/constants.py
commonz/convert/colors.py
commonz/convert/data.py
commonz/convert/numbers.py
commonz/convert/text.py
commonz/datafiles/eml.py
commonz/datafiles/html.py
commonz/datafiles/ini.py
commonz/datafiles/jon.py
commonz/datafiles/mtl.py
commonz/datafiles/obj.py
commonz/datafiles/tsv.py
commonz/datafiles/txt.py
commonz/datafiles/yml.py
commonz/ds/chain.py
commonz/ds/matrix.py
commonz/ds/quaternion.py
commonz/ds/table.py
commonz/ds/vector.py
commonz/fs/actions.py
commonz/fs/checks.py
commonz/fs/hashers.py
commonz/fs/pathnames.py
commonz/fs/permits.py
commonz/fs/temps.py
commonz/fs/timers.py
commonz/geometry/circular.py
commonz/geometry/curves.py
commonz/geometry/polyhedra.py
commonz/io/tty.py
commonz/logger/__init__.py
commonz/logger/logger.py
commonz/net/aws.py
commonz/net/client.py
commonz/net/ftp.py
commonz/net/server.py
commonz/timer/__init__.py
commonz/timer/timer.py
commonz-1.0.0.dist-info/METADATA
commonz-1.0.0.dist-info/WHEEL
commonz-1.0.0.dist-info/top_level.txt
commonz-1.0.0.dist-info/RECORD
