Metadata-Version: 2.1
Name: commonz
Version: 1.0.0
Summary: Python modules for selecting,grouping,simplifying the common tasks
Home-page: https://github.com/N-z0/CommonZ
Author: ('N-z0',)
Author-email: syslog@laposte.net
Maintainer: ('N-z0',)
Maintainer-email: syslog@laposte.net
License: Public Domain
Download-URL: https://github.com/N-z0/CommonZ/releases
Keywords: general,common,development,library
Platform: GNU/Linux
Classifier: Development Status :: 5 - Production/Stable
Classifier: Intended Audience :: Developers
Classifier: Topic :: Software Development
Classifier: Topic :: Software Development :: Libraries
Classifier: Topic :: Software Development :: Libraries :: Application Frameworks
Classifier: Topic :: Software Development :: Libraries :: Python Modules
Classifier: License :: Public Domain
Classifier: Operating System :: POSIX :: Linux
Classifier: Programming Language :: Python
Classifier: Programming Language :: Python :: 3
Classifier: Programming Language :: Python :: 3.6
Classifier: Programming Language :: Python :: 3.7
Classifier: Programming Language :: Python :: 3.8
Classifier: Programming Language :: Python :: 3.9
Classifier: Programming Language :: Python :: 3.10
Classifier: Programming Language :: Python :: 3 :: Only
Requires-Python: >=3, <4
Requires-Dist: Pillow (<9,>=8)
Requires-Dist: PyGObject (<4,>=3)
Requires-Dist: boto3 (<2,>=1)
Requires-Dist: numpy (<2,>=1)
Requires-Dist: opencv-contrib-python (<5,>=4)
Requires-Dist: pycairo (<2,>=1)
Requires-Dist: rsa (<4,>=3)
Requires-Dist: ruamel.yaml (<1,>=0)
